cachier/__init__.py
cachier/__main__.py
cachier/_types.py
cachier/_version.py
cachier/config.py
cachier/core.py
cachier/py.typed
cachier/version.info
cachier/cores/__init__.py
cachier/cores/base.py
cachier/cores/memory.py
cachier/cores/mongo.py
cachier/cores/pickle.py
cachier/cores/redis.py
cachier/cores/sql.py
cachier-4.0.0.dist-info/licenses/LICENSE
cachier-4.0.0.dist-info/METADATA
cachier-4.0.0.dist-info/WHEEL
cachier-4.0.0.dist-info/entry_points.txt
cachier-4.0.0.dist-info/top_level.txt
cachier-4.0.0.dist-info/RECORD
