Metadata-Version: 2.4
Name: cachier
Version: 4.0.0
Summary: Persistent, stale-free, local and cross-machine caching for Python functions.
Author-email: Shay Palachy Affek <shay.palachy@gmail.com>
License: MIT License
Project-URL: Source, https://github.com/python-cachier/cachier
Keywords: cache,caching,cross-machine,decorator,local,memoization,mongo,persistent
Classifier: Development Status :: 4 - Beta
Classifier: Intended Audience :: Developers
Classifier: License :: OSI Approved :: MIT License
Classifier: Programming Language :: Python
Classifier: Programming Language :: Python :: 3 :: Only
Classifier: Programming Language :: Python :: 3.9
Classifier: Programming Language :: Python :: 3.10
Classifier: Programming Language :: Python :: 3.11
Classifier: Programming Language :: Python :: 3.12
Classifier: Programming Language :: Python :: 3.13
Classifier: Topic :: Other/Nonlisted Topic
Classifier: Topic :: Software Development :: Libraries
Classifier: Topic :: Software Development :: Libraries :: Python Modules
Classifier: Topic :: Utilities
License-File: LICENSE
Requires-Dist: portalocker>=2.3.2
Requires-Dist: watchdog>=2.3.1
Dynamic: license-file
